mtcheckbot/__init__.py
mtcheckbot/checkmt.py
mtcheckbot-0.2.dist-info/METADATA
mtcheckbot-0.2.dist-info/WHEEL
mtcheckbot-0.2.dist-info/top_level.txt
mtcheckbot-0.2.dist-info/RECORD
